simuran/__init__.py
simuran/recording.py
simuran/recording_container.py
simuran/analysis/__init__.py
simuran/analysis/analysis_handler.py
simuran/analysis/unit.py
simuran/bridges/__init__.py
simuran/bridges/allen_vbn_bridge.py
simuran/bridges/ibl_wide_bridge.py
simuran/bridges/mne_bridge.py
simuran/bridges/neo_bridge.py
simuran/bridges/neurochat_bridge.py
simuran/core/__init__.py
simuran/core/base_class.py
simuran/core/base_container.py
simuran/core/base_signal.py
simuran/core/log_handler.py
simuran/core/param_handler.py
simuran/core/utils.py
simuran/loaders/__init__.py
simuran/loaders/allen_loader.py
simuran/loaders/base_loader.py
simuran/loaders/loader_list.py
simuran/loaders/neurochat_loader.py
simuran/loaders/nwb_loader.py
simuran/loaders/one_loader.py
simuran/plot/__init__.py
simuran/plot/base_plot.py
simuran/plot/figure.py
simuran/plot/signal.py
simuran/plot/unit.py
simuran/ui/__init__.py
simuran/ui/common.py
simuran/ui/node.py
simuran/ui/node_elements.py
simuran/ui/node_factories.py
simuran/ui/simuran_ui.py
simuran/ui/nodes/__init__.py
simuran/ui/nodes/lfp_node.py
simuran/ui/nodes/python_node.py
simuran/ui/nodes/recording_node.py
simuran-23.8.0.dist-info/LICENSE
simuran-23.8.0.dist-info/METADATA
simuran-23.8.0.dist-info/WHEEL
simuran-23.8.0.dist-info/entry_points.txt
simuran-23.8.0.dist-info/top_level.txt
simuran-23.8.0.dist-info/RECORD
