Metadata-Version: 2.1
Name: simuran
Version: 23.8.0
Summary: Simultaneous Multi-region Analysis supported with a network style
Home-page: https://github.com/seankmartin/SIMURAN
Download-URL: https://github.com/seankmartin/SIMURAN
Author: Sean K. Martin
Author-email: martins7@tcd.ie
License: GNU GPL
Project-URL: Bug Tracker, https://github.com/seankmartin/SIMURAN/issues
Project-URL: Documentation, https://simuran.readthedocs.io
Keywords: neuroscience,network,gui,api
Classifier: Intended Audience :: Education
Classifier: Intended Audience :: Science/Research
Classifier: Programming Language :: Python :: 3
Classifier: Topic :: Scientific/Engineering
Classifier: Topic :: Scientific/Engineering :: Visualization
Classifier: Topic :: Scientific/Engineering :: Information Analysis
Classifier: Operating System :: POSIX
Classifier: Operating System :: Unix
Classifier: Operating System :: MacOS
Classifier: Operating System :: Microsoft :: Windows
Requires-Python: >=3.7
License-File: LICENSE
Requires-Dist: numpy >=1.15.0
Requires-Dist: skm-pyutils
Requires-Dist: seaborn
Requires-Dist: indexed
Requires-Dist: tqdm
Requires-Dist: mne
Requires-Dist: rich
Requires-Dist: dearpygui >=1.9.0
Requires-Dist: typer
Requires-Dist: click-spinner
Requires-Dist: mpire
Provides-Extra: docs
Requires-Dist: sphinx ; extra == 'docs'
Requires-Dist: sphinxcontrib-apidoc ; extra == 'docs'
Requires-Dist: sphinx-rtd-theme ; extra == 'docs'
Requires-Dist: pygments ; extra == 'docs'
Provides-Extra: neurochat
Requires-Dist: neurochat ; extra == 'neurochat'
Provides-Extra: tests
Requires-Dist: neurochat ; extra == 'tests'
Requires-Dist: pytest ; extra == 'tests'
Requires-Dist: pytest-cov ; extra == 'tests'
Requires-Dist: coverage[toml] ; extra == 'tests'
Requires-Dist: pynwb ; extra == 'tests'
